fastosteoid.cpython-312-aarch64-linux-gnu.so
osteoid/__init__.py
osteoid/exceptions.py
osteoid/lib.py
osteoid/skeleton.py
osteoid/util.py
osteoid/viewer.py
osteoid-0.6.0.dist-info/METADATA
osteoid-0.6.0.dist-info/WHEEL
osteoid-0.6.0.dist-info/top_level.txt
osteoid-0.6.0.dist-info/RECORD
osteoid-0.6.0.dist-info/licenses/LICENSE
