Metadata-Version: 2.4
Name: osteoid
Version: 0.6.0
Summary: Skeleton object used for representing neurons, adjacent cells, and organelles.
Author-email: William Silversmith <william.silversmith@gmail.com>
License: BSD-3 Clause
Requires-Python: >=3.9
License-File: LICENSE
Requires-Dist: fastremap<2.0.0,>=1.16.0
Requires-Dist: networkx<4.0.0,>=3.0.0
Requires-Dist: numpy<3.0.0,>=1.17.0
Requires-Dist: pybind11
Dynamic: license-file
